vet/__init__.py
vet/commands.py
vet/models/__init__.py
vet/models/audits.py
vet/models/common.py
vet/models/config.py
vet/models/imports_lock.py
vet/poetry_entrypoint.py
vet/scripts/__init__.py
vet/scripts/generate_schemas.py
vet/tests/__init__.py
vet/tests/conftest.py
vet/tests/resources/dummy_repo/poetry.lock
vet/tests/resources/dummy_repo/pyproject.toml
vet/tests/test_commands.py
vet/tests/test_config.py
vet/texts.py
vet/utils.py
vet-0.1.1.post4.dist-info/LICENSE
vet-0.1.1.post4.dist-info/METADATA
vet-0.1.1.post4.dist-info/WHEEL
vet-0.1.1.post4.dist-info/entry_points.txt
vet-0.1.1.post4.dist-info/RECORD
