Metadata-Version: 2.1
Name: vet
Version: 0.1.1.post4
Summary: A poetry plugin for establishing chain of trust
Author: Rafael Irgolic
Author-email: hello@irgolic.com
Requires-Python: >=3.10,<4.0
Classifier: Programming Language :: Python :: 3
Classifier: Programming Language :: Python :: 3.10
Classifier: Programming Language :: Python :: 3.11
Classifier: Programming Language :: Python :: 3.12
Requires-Dist: msgspec (>=0.18.6,<0.19.0)
Requires-Dist: poetry (>=1.8.2,<2.0.0)
Requires-Dist: tomli-w (>=1.0.0,<2.0.0)
Requires-Dist: typing-extensions (>=4.10.0,<5.0.0)
